{
  "_id": "671ef0f25279bcfb3c1e24ca",
  "pokemonId": "A1-008",
  "name": "Weedle",
  "pack": "Mewtwo",
  "abilities": [],
  "alternateArt": false,
  "cardType": "Pokemon",
  "energyType": [
    "Grass"
  ],
  "hp": "50",
  "moves": [
    {
      "name": "Sting",
      "energyCost": [
        "Grass"
      ],
      "hp": "20",
      "_id": "67994e671552ba8d13d72f1c"
    }
  ],
  "obtain": [
    {
      "source": {
        "_id": "6721ceb3423ed078c0a1f5d2",
        "type": "Normal Pack",
        "expires": null,
        "name": "Genetic Apex: Mewtwo",
        "linkedArticle": {
          "_id": "6728e6038cfb55d02155f843",
          "title": "Genetic Apex: Mewtwo",
          "url": "/sets/genetic-apex-mewtwo/",
          "image": "/pkm_img/Sets/GeneticApexMewtwo.webp"
        }
      },
      "amount": 1,
      "type": "sets"
    }
  ],
  "rarity": "d-1",
  "release": "2024-10-30T03:00:00.000Z",
  "retreat": 1,
  "subType": "Basic",
  "weakness": [
    "Fire"
  ],
  "popRank": 198,
  "artVariants": [],
  "limitlessId": "A1 8"
}