{
  "_id": "671ef0f25279bcfb3c1e2584",
  "pokemonId": "A1-194",
  "name": "Wigglytuff",
  "pack": "Pikachu",
  "abilities": [],
  "alternateArt": false,
  "cardType": "Pokemon",
  "energyType": [
    "Colorless"
  ],
  "hp": "100",
  "moves": [
    {
      "name": "Hyper Voice",
      "energyCost": [
        "Colorless",
        "Colorless"
      ],
      "hp": "60",
      "_id": "67994d5f97fb8e77af07c5e0"
    }
  ],
  "obtain": [
    {
      "source": {
        "_id": "6721ca53f3133dff28feb0ce",
        "type": "Normal Pack",
        "expires": null,
        "name": "Genetic Apex: Pikachu",
        "linkedArticle": {
          "_id": "6728e5c17e99ebe6207c6c2e",
          "title": "Genetic Apex: Pikachu",
          "url": "/sets/genetic-apex-pikachu/",
          "image": "/pkm_img/Sets/GeneticApexPikachu.webp"
        }
      },
      "amount": 1,
      "type": "sets"
    }
  ],
  "rarity": "d-1",
  "retreat": 2,
  "subType": "Stage 1",
  "weakness": [
    "Fighting"
  ],
  "release": "2024-10-30T03:00:00.000Z",
  "popRank": 1.7976931348623157e+308,
  "artVariants": [],
  "limitlessId": "A1 194",
  "deckTypes": []
}